[
    {
        "_id" : "68c95b7fc4d2993c4c0e5bb7",
        "title" : "changeUserPhone",
        "inputs" : [ "phone", "random" ],
        "text" : "سیستم مدیریت محتوای کامز\nبرای تایید تغییر شماره حساب خود به $phone کد زیر را وارد کنید\nکد: $random \nلغو11",
        "sendOTP" : true,
      
        "isCore" : true
    },
    {   
        "title" : "rigisterPhoneNumber",
        "sendOTP": true,
        "text" : "سیسیتم مدیریت محتوای کامز code : $random \n لغو11 ",
        "inputs": [
            "random"
        ],
        "isCore" : true
    },
    {
        "_id": "680dea344ae64049f023d876",
        "title": "loanEdited",
        "inputs": [
            "trackingCode"
        ],
        "text": "سیستم مدیریت محتوای کامز\nوام شما با کد پیگیری $trackingCode ویرایش شد\nلغو11",
        "sendOTP": true,
        "status": "waiting",
        "isCore": false,
        "__v": 0
    },
    {
        "_id": "680cc98e6d80288a9f3e9ff1",
        "title": "paymentRejected",
        "inputs": [
            "paymentType",
            "trackingCode",
            "rejectionReason"
        ],
        "text": "سیستم مدیریت محتوای کامز\nپرداخت $paymentType با کد پیگیری $trackingCode رد شد\nدلیل رد درخواست: $rejectionReason\nلغو11",
        "sendOTP": true,
        "status": "waiting",
        "isCore": false,
        "__v": 0
    },
    {
        "_id": "680cc5e75c3ad6f061054071",
        "title": "paymentConfirmed",
        "inputs": [
            "paymentType",
            "trackingCode"
        ],
        "text": "سیستم مدیریت محتوای کامز\nپرداخت $paymentType شما با کد پیگیری $trackingCode تایید شد\nلغو11",
        "sendOTP": true,
        "status": "waiting",
        "isCore": false,
        "__v": 0
    },
    {
        "_id": "680cba24d69a4378318a0df8",
        "title": "checkReturned",
        "inputs": [
            "checkNumber",
            "trackingCode"
        ],
        "text": "سیستم مدیریت محتوای کامز\nچک به شماره $checkNumber برگشت خورده\nلطفا در اسرع وقت نسبت به بررسی و رفع مشکل اقدام کنید\nکد پیگیری: $trackingCode\nلغو11",
        "sendOTP": true,
        "status": "waiting",
        "isCore": false,
        "__v": 0
    },
    {
        "_id": "680cb6517b90025b39136480",
        "title": "checkEdited",
        "inputs": [
            "checkNumber",
            "trackingCode"
        ],
        "text": "سیستم مدیریت محتوای کامز\nچک به شماره $checkNumber ویرایش شد\nکد رهگیری: $trackingCode\nلغو11",
        "sendOTP": true,
        "status": "waiting",
        "isCore": false,
        "__v": 0
    },
    {
        "_id": "680c9cd177407207486820dd",
        "title": "checkRejected",
        "inputs": [
            "checkNumber",
            "rejectionReason",
            "trackingCode"
        ],
        "text": "سیستم مدیریت محتوای کامز\nچک به شماره $checkNumber رد شد\nدلیل رد: $rejectionReason\nکد رهگیری: $trackingCode\nلغو11",
        "sendOTP": true,
        "status": "waiting",
        "isCore": false,
        "__v": 0
    },
    {
        "_id": "680c9a007740720748681f16",
        "title": "checkApproved",
        "inputs": [
            "checkNumber",
            "trackingCode"
        ],
        "text": "سیستم مدیریت محتوای کامز\nچک به شماره $checkNumber تایید شد\nکد رهگیری: $trackingCode\nلغو11",
        "sendOTP": true,
        "status": "waiting",
        "isCore": false,
        "__v": 0
    },
    {
        "_id": "6808d4e83c5e60963674f88b",
        "title": "installmentsRejected",
        "inputs": [
            "trackingCode",
            "paymentType",
            "rejectionReason"
        ],
        "text": "سیستم مدیریت محتوای کامز\n$paymentType شما رد شد\nدلیل: $rejectionReason\nکد پیگیری: $trackingCode\nلغو11",
        "sendOTP": true,
        "status": "waiting",
        "isCore": false,
        "__v": 0
    },
    {
        "_id": "6808d3a5980e45b215435903",
        "title": "installmentsApproved",
        "inputs": [
            "trackingCode",
            "paymentType"
        ],
        "text": "سیستم مدیریت محتوای کامز\n$paymentType شما با موفقیت تایید شد\nکد پیگیری: $trackingCode\nلغو11",
        "sendOTP": true,
        "status": "waiting",
        "isCore": false,
        "__v": 0
    },
    {
        "_id": "6808d19b980e45b2154357e9",
        "title": "chequePaymentRejected",
        "inputs": [
            "trackingCode",
            "chequeNumber",
            "paymentType",
            "rejectionReason"
        ],
        "text": "سیستم مدیریت محتوای کامز\nچک پرداخت $paymentType شما به شماره $chequeNumber رد شد\nدلیل: $rejectionReason\nکد پیگیری پرداخت: $trackingCode\nلغو11",
        "sendOTP": true,
        "status": "waiting",
        "isCore": false,
        "__v": 0
    },
    {
        "_id": "6808ce1ada1bcab08f2b5c1b",
        "title": "chequePaymentApproved",
        "inputs": [
            "trackingCode",
            "chequeNumber",
            "paymentType"
        ],
        "text": "سیستم مدیریت محتوای کامز\nچک پرداخت $paymentType شما به شماره $chequeNumber با موفقیت تایید شد\nکد پیگیری پرداخت: $trackingCode\nلغو11",
        "sendOTP": true,
        "status": "waiting",
        "isCore": false,
        "__v": 0
    },
    {
        "_id": "6808cca499dbc76500d21494",
        "title": "invoicePaymentCanceled",
        "inputs": [
            "trackingCode",
            "factorNumber"
        ],
        "text": "سیستم مدیریت محتوای کامز\nدرخواست پرداخت شما برای فاکتور به شماره $factorNumber لغو شد\nکد پیگیری: $trackingCode\nلغو11",
        "sendOTP": true,
        "status": "waiting",
        "isCore": false,
        "__v": 0
    },
    {
        "_id": "6808cac9d2f9515a924aecba",
        "title": "increaseWalletRequestCanceled",
        "inputs": [
            "trackingCode"
        ],
        "text": "سیستم مدیریت محتوای کامز\nدرخواست افزایش موجودی حساب شما لغو شد\nکد پیگیری: $trackingCode\nلغو11",
        "sendOTP": true,
        "status": "waiting",
        "isCore": false,
        "__v": 0
    },
    {
        "_id": "6808ba37cc2bed4f26fb51a0",
        "title": "invoicePayment",
        "inputs": [
            "trackingCode",
            "facorNumber",
            "remainingAmount"
        ],
        "text": "سیستم مدیریت محتوای کامز\nپرداخت شما برای فاکتور شماره $facorNumber ثبت شد\nمبلغ باقی مانده : $remainingAmount تومان\nکد پیگیری : $trackingCode\nلغو11",
        "sendOTP": true,
        "status": "waiting",
        "isCore": false,
        "__v": 0
    },
    {
        "_id": "6808a39e2186b0d1ec60132d",
        "title": "createLoan",
        "inputs": [
            "trackingCode"
        ],
        "text": "سیستم مدیریت محتوای کامز\nوام شما با کد پیگیری $trackingCode ثبت شد\nلغو11",
        "sendOTP": true,
        "status": "waiting",
        "isCore": false,
        "__v": 0
    },
    {
        "_id": "6808a102cf05c4cbf7bfb168",
        "title": "checksAdded",
        "inputs": [
            "trackingCode"
        ],
        "text": "سیستم مدیریت محتوای کامز\nچک‌های مربوط به وام شما تایید شد\nکد پیگیری: $trackingCode\nلغو11",
        "sendOTP": true,
        "status": "waiting",
        "isCore": false,
        "__v": 0
    },
    {
        "_id": "6807a9f5b1be88052c01442f",
        "title": "notifyLoanStatus",
        "inputs": [
            "trackingCode",
            "processTitle"
        ],
        "text": "سیستم مدیریت محتوای کامز\n$processTitle وام شما با موفقیت انجام شد\nکد پیگیری: $trackingCode\nلغو11",
        "sendOTP": true,
        "status": "waiting",
        "isCore": false,
        "__v": 0
    },
    {
        "_id": "6807a805192d0836515ea37d",
        "title": "increaseWalletReqAdded",
        "inputs": [
            "trackingCode"
        ],
        "text": "سیستم مدیریت محتوای کامز\nدرخواست افزایش موجودی شما ثبت شد\nکد پیگیری: $trackingCode\nلغو11",
        "sendOTP": true,
        "status": "waiting",
        "isCore": false,
        "__v": 0
    },
    {
        "_id": "68062119585608d7491ceb9a",
        "title": "walletIncreaseRejected",
        "inputs": [
            "trackingCode",
            "amount"
        ],
        "text": "سیستم مدیریت محتوای کامز\nدرخواست افزایش موجودی حساب شما رد شد،برای بررسی دلیل رد درخواست به پنل کاربری خود مراجعه کنید\nکد پیگیری: $trackingCode\nلغو11",
        "sendOTP": true,
        "status": "waiting",
        "isCore": false,
        "__v": 0
    },
    {
        "_id": "68061ffc585608d7491ceb09",
        "title": "walletIncreased",
        "inputs": [
            "trackingCode",
            "amount"
        ],
        "text": "سیستم مدیریت محتوای کامز\nافزایش موجودی حساب شما به مبلغ $amount انجام شد\nکد پیگیری: $trackingCode\nلغو11",
        "sendOTP": true,
        "status": "waiting",
        "isCore": false,
        "__v": 0
    },
    {
        "_id": "67fbc7e1ba4206d2ff3ce62a",
        "title": "requestSubmitReturnCheck",
        "inputs": [
            "code",
            "checkNumber"
        ],
        "text": "سیستم مدیریت محتوای کامز\nبرای تایید مرجوعی چک ب شماره  $checkNumber کد زیر را ارسال کنید\nکد : $code\nلغو11",
        "sendOTP": true,
        "status": "waiting",
        "isCore": true,
        "__v": 0
    },
    {
        "_id": "67d823d3cff27744866c6f04",
        "title": "retakeReturnedCheck",
        "inputs": [
            "code"
        ],
        "text": "سیستم مدیریت محتوای کامز\nلطفا کد زیر را برای تایید پس دادن چک وارد کنید\nکد :$code \nلغو11",
        "sendOTP": true,
        "status": "waiting",
        "isCore": true,
        "__v": 0
    },
    {
        "_id": "67d82212cff27744866c6e21",
        "title": "returnCheckTrakingCode",
        "inputs": [
            "trackingCode"
        ],
        "text": "سیستم مدیریت محتوای کامز\nکد رهگیری درخواست مرجوعی:$trackingCode\nلغو11",
        "sendOTP": true,
        "status": "waiting",
        "isCore": true,
        "__v": 0
    },
    {
        "_id": "67d82125cff27744866c6da3",
        "title": "confirmReturnCheck",
        "inputs": [
            "code",
            "checkNumber"
        ],
        "text": "سیستم مدیریت محتوای کامز\nبرای تایید مرجوعی چک ب شماره  $checkNumber کد زیر را ارسال کنید\nکد : $code\nلغو11",
        "sendOTP": true,
        "status": "waiting",
        "isCore": true,
        "__v": 0
    },
    {
        "_id": "670a36f9c360f3fd0eed4174",
        "title": "verifyBackup",
        "inputs": [
            "random"
        ],
        "text": "سیسیتم مدیریت محتوای کامز code : $random \n لغو:11 ",
        "sendOTP": true,
        "status": "waiting",
        "isCore": false,
        "__v": 0
    },
    {
        "_id": "66dc3d117e39bdba6bf1dffc",
        "title": "userAdded",
        "inputs": [
            "password"
        ],
        "text": "سلام به سیستم مدیریت محتوای کامز خوش آمدید رمز موقت در زیر است $password",
        "defaultSmsConfig": "d40d0261f9d00f881d926311",
        "sendOTP": true,
        "status": "waiting",
        "isCore": false,
        "__v": 0
    },
    {
        "_id": "66d2fef18dd05d0d077a75a2",
        "title": "commentReply",
        "inputs": [
            "url"
        ],
        "text": "سوال شما پاسخ داده شد برای مشاهده پاسخ به این لینک مراجعه کنید: $url \n لغو:11",
        "sendOTP": true,
        "status": "waiting",
        "isCore": false,
        "__v": 0
    },
    {
        "_id": "66b9c376fe4b79374b920c6d",
        "title": "userCommentRegister",
        "inputs": [
            "random"
        ],
        "text": "سیسیتم مدیریت محتوای کامز code : $random \n لغو:11 ",
        "sendOTP": true,
        "status": "waiting",
        "isCore": true,
        "__v": 0
    },
    {
        "_id": "6543a364058c610ffa7a015c",
        "title": "publishConfirmation",
        "inputs": [
            "title"
        ],
        "text": "سیستم مدیریت محتوای کامز مقاله‌ی جدید ثبت شده لطفا برای تایید انتشار به سایت مراجعه کنید عنوان : $title \n لغو:11",
        "sendOTP": true,
        "status": "waiting",
        "isCore": false,
        "apiCreator": "2e90bbca1c83f2784b67baec",
        "__v": 0
    },
    {
        "_id": "64e0b62062a6bf85dc1a2c89",
        "title": "adminAdded",
        "inputs": [
            "password"
        ],
        "text": "سلام به سیستم مدیریت محتوای کامز خوش آمدید رمز موقت در زیر است $password",
        "sendOTP": true,
        "status": "waiting",
        "isCore": false,
        "__v": 0
    },
    {
        "_id": "64b9052c25b244b5ab66510c",
        "title": "sendUserPassword",
        "inputs": [
            "password",
            "name",
            "family"
        ],
        "text": " کامز سیستم مدیریت محتوا \n قالب تایید شد شماره قالب :$password  \n ",
        "sendOTP": true,
        "status": "waiting",
        "isCore": false,
        "__v": 0
    },
    {
        "_id": "649422192b475c6bdcee9ea2",
        "title": "templateConfirmed",
        "inputs": [
            "id",
            "name",
            "family"
        ],
        "text": " کامز سیستم مدیریت محتوا \n قالب تایید شد شماره قالب :$id  \n ",
        "sendOTP": true,
        "status": "waiting",
        "isCore": false,
        "__v": 0
    },
    {
        "_id": "649421f02b475c6bdcee9e9f",
        "title": "templateRejected",
        "inputs": [
            "id",
            "name",
            "family"
        ],
        "text": " کامز سیستم مدیریت محتوا \n قالب رد شد شماره قالب :$id  \n ",
        "sendOTP": true,
        "status": "waiting",
        "isCore": false,
        "__v": 0
    },
    {
        "_id": "6493fb9422bb66d74999db28",
        "title": "helloTest1",
        "inputs": [
            "name",
            "random"
        ],
        "text": " کامز سیستم مدیریت محتوا \n ید شماره تلفن کد زیر را در سایت وارد کن $name \n ",
        "sendOTP": true,
        "status": "waiting",
        "isCore": false,
        "__v": 0
    },
    {
        "_id": "6493fa83ee29b60503107459",
        "title": "helloTest",
        "inputs": [
            "name",
            "random"
        ],
        "text": "ید شماره تلفن کد زیر را در سایت وارد کن $name",
        "sendOTP": true,
        "status": "waiting",
        "isCore": false,
        "__v": 0
    },
   
    {
        "_id": "63ce66dcce9a92171c11a1cb",
        "inputs": [
            "name",
            "random"
        ],
        "title": "adminAddPhone",
        "sendOTP": true,
        "text": "سیستم مدیریت محتوای کامز $name عزیز در صورت تایید شماره تلفن کد زیر را در سایت وارد کنید کد تایید شماره تلفن :$random"
    },
    {
        "_id": "626faebf0cade02db86bf32b",
        "inputs": [
            "keyWord",
            "url",
            "change"
        ],
        "title": "checkKeywordsResult",
        "sendOTP": true,
        "text": "سیستم مدیریت محتوای کامزدر عبارت $keyWord سایت $url تغییرات داده است تغییرات : $change",
        "__v": 0
    },
    {
        "_id": "625bf0b016b3c2acca416d00",
        "inputs": [
            "random",
            "name",
            "phoneNumber"
        ],
        "sendOTP": true,
        "title": "changePhoneChekUser",
        "text": "سیستم مدیریت محتوای کامز $name عزیز برای تایید تغییر شماره خود کد ارسال شده را وارد کنید کد رندوم : $random",
        "__v": 0
    },
    {
        "_id": "625befa40e5ce99bb2dc8228",
        "inputs": [
            "random"
        ],
        "title": "disableTowFactorCodeUser",
        "sendOTP": true,
        "text": "سیستم مدیریت محتوای کامز کد تایید غیر فعال کردن ورود دومرحله ای : $random",
        "__v": 0
    },
    {
        "_id": "6257de0b8719221ef9278d2f",
        "inputs": [
            "random",
            "name",
            "phoneNumber"
        ],
        "title": "changePhoneChekServiceProvider",
        "sendOTP": true,
        "text": "سیستم مدیریت محتوای کامز $name عزیز برای تایید تغییر شماره خود کد ارسال شده را وارد کنید کد رندوم : $random",
        "__v": 0
    },
    {
        "_id": "6257dcc38719221ef9278d2d",
        "inputs": [
            "random"
        ],
        "title": "disableTowFactorCodeServiceProvider",
        "sendOTP": true,
        "text": "سیستم مدیریت محتوای کامز کد تایید غیر فعال کردن ورود دومرحله ای : $random",
        "__v": 0
    },
    {
        "_id": "6241b87dc80556f07ae6aa2c",
        "inputs": [
            "name",
            "random"
        ],
        "title": "changePhoneChek",
        "sendOTP": true,
        "text": "سیستم مدیریت محتوای کامز $name  عزیز برای تایید تغییر شماره خود کد ارسال شده را وارد کنیدکد رندوم : $random",
        "__v": 0
    },
    {
        "_id": "623eecd6f6653f6634492749",
        "inputs": [
            "random"
        ],
        "title": "disableTowFactorCode",
        "sendOTP": true,
        "text": "سیستم مدیریت محتوای کامز کد تایید غیر فعال کردن ورود دومرحله ای : $random",
        "__v": 0
    },
    {
        "_id": "62330b99fb5779b59944b0a7",
        "inputs": [
            "random"
        ],
        "title": "sendWithOtherWay",
        "sendOTP": true,
        "text": "سیستم مدیریت محتوای کامز کد تایید غیر فعال کردن ورود دومرحله ای : $random",
        "__v": 0
    },
    {
        "_id": "622f1a728d83c30b28cf9f1a",
        "inputs": [
            "name",
            "random"
        ],
        "title": "adminLogInWithRandom",
        "sendOTP": true,
        "text": "سیستم مدیریت محتوای کامز $name عزیز خوش آمدید کد فعالسازی : $random",
        "__v": 0
    },
    {
        "_id": "622dc4d2d8f27d7fb50d4766",
        "inputs": [
            "count",
            "name"
        ],
        "title": "CumulativeFaq",
        "sendOTP": true,
        "text": "سیسیتم مدیریت محتوای کامز $name عزیز $count  سوال جدید در سیستم ثبت شده است",
        "__v": 0
    },
    {
        "_id": "62289c01a790c0e92e94ee1a",
        "inputs": [
            "name"
        ],
        "title": "newFaq",
        "sendOTP": true,
        "text": "cms کامز $name عزیز سوال جدیدی در سیستم ثبت شده است",
        "__v": 0
    }
]